git_commitflow/__init__.py
git_commitflow/cache_file.py
git_commitflow/git_commitflow.py
git_commitflow/helpers.py
git_commitflow/readline_manager.py
git_commitflow-1.1.4.dist-info/licenses/LICENSE
git_commitflow-1.1.4.dist-info/METADATA
git_commitflow-1.1.4.dist-info/WHEEL
git_commitflow-1.1.4.dist-info/entry_points.txt
git_commitflow-1.1.4.dist-info/top_level.txt
git_commitflow-1.1.4.dist-info/RECORD
